tester_vbot3/__init__.py
test_helper_vbot3-1.5.dist-info/LICENSE
test_helper_vbot3-1.5.dist-info/METADATA
test_helper_vbot3-1.5.dist-info/WHEEL
test_helper_vbot3-1.5.dist-info/top_level.txt
test_helper_vbot3-1.5.dist-info/RECORD
