Metadata-Version: 2.1
Name: test-helper-vbot3
Version: 1.5
Summary: Tester for Vbot3
Home-page: https://github.com/vb64/test.helper.vbot3
Author: Vitaly Bogomolov
Author-email: mail@vitaly-bogomolov.ru
Project-URL: Bug Tracker, https://github.com/vb64/test.helper.vbot3/issues
Classifier: Programming Language :: Python :: 3
Classifier: License :: OSI Approved :: MIT License
Classifier: Operating System :: OS Independent
Requires-Python: >=3.7
License-File: LICENSE
Requires-Dist: telemulator3 (==1.4)
Requires-Dist: tester-flask (==1.2)
Requires-Dist: test-helper-gae3 (==1.2)
